wagtailimagecaptions/__init__.py
wagtailimagecaptions/apps.py
wagtailimagecaptions/models.py
wagtailimagecaptions/services.py
wagtailimagecaptions/signals.py
wagtailimagecaptions/migrations/0001_initial.py
wagtailimagecaptions/migrations/0002_rename_extendedrendition_captionedrendition.py
wagtailimagecaptions/migrations/0003_captionedimage_byline_and_more.py
wagtailimagecaptions/migrations/0004_auto_20231121_1134.py
wagtailimagecaptions/migrations/0005_auto_20231121_1134.py
wagtailimagecaptions/migrations/0006_alter_captionedimage_options.py
wagtailimagecaptions/migrations/0007_captionedimage_description.py
wagtailimagecaptions/migrations/__init__.py
wagtailimagecaptions-0.2.6.dist-info/LICENSE
wagtailimagecaptions-0.2.6.dist-info/WHEEL
wagtailimagecaptions-0.2.6.dist-info/METADATA
wagtailimagecaptions-0.2.6.dist-info/RECORD
